awslambdalawm/__init__.py
awslambdalawm/httpapi/__init__.py
awslambdalawm/httpapi/__impl/__init__.py
awslambdalawm/httpapi/__impl/app.py
awslambdalawm/httpapi/__impl/app_unittest.py
awslambdalawm/httpapi/__impl/domain.py
awslambdalawm/httpapi/__impl/principalparser.py
awslambdalawm/httpapi/__impl/principalparser_unittest.py
awslambdalawm/security/__init__.py
awslambdalawm/security/authz/__init__.py
awslambdalawm/security/authz/__impl/__init__.py
awslambdalawm/security/authz/__impl/domain.py
awslambdalawm/security/authz/__impl/exception.py
awslambdalawm/security/authz/__impl/pdprepo.py
awslambdalawm/security/authz/__impl/pdpservice.py
awslambdalawm/security/authz/__impl/pdpservice_unittest.py
awslambdalawm/security/authz/__impl/pep.py
awslambdalawm/security/authz/__impl/pep_unittest.py
awslambdalawm/security/core/__init__.py
awslambdalawm/security/core/__impl/__init__.py
awslambdalawm/security/core/__impl/context.py
awslambdalawm/security/core/__impl/domain.py
awslambdalawm/util/__init__.py
awslambdalawm/util/__impl/__init__.py
awslambdalawm/util/__impl/datetimeutil.py
awslambdalawm/util/__impl/datetimeutil_unittest.py
awslambdalawm/util/__impl/objectutil.py
awslambdalawm/util/__impl/objectutil_unittest.py
awslambda_python_common-0.0.65.dist-info/METADATA
awslambda_python_common-0.0.65.dist-info/WHEEL
awslambda_python_common-0.0.65.dist-info/top_level.txt
awslambda_python_common-0.0.65.dist-info/RECORD
