Metadata-Version: 2.1
Name: awslambda-python-common
Version: 0.0.65
Summary: AWS Lambda Python development framework
Home-page: https://gitlab.com/lm-private/awslambda-python-common
Author: Lawrence M
Author-email: lawrence.mok@gmail.com
License: UNKNOWN
Platform: UNKNOWN
Requires-Python: >=3.6
Requires-Dist: pyjwt
Requires-Dist: dacite
Requires-Dist: aws-lambda-powertools
